{
  "realm": "myrealm",
  "enabled": true,
  "requiredActions": [
    { "alias": "VERIFY_EMAIL", "enabled": false },
    { "alias": "UPDATE_PROFILE", "enabled": false },
    { "alias": "UPDATE_PASSWORD", "enabled": false },
    { "alias": "TERMS_AND_CONDITIONS", "enabled": false }
  ],
  "clients": [
    {
      "clientId": "notification-service",
      "protocol": "openid-connect",
      "publicClient": false,
      "standardFlowEnabled": false,
      "directAccessGrantsEnabled": true,
      "fullScopeAllowed": true,
      "serviceAccountsEnabled": true,
      "clientAuthenticatorType": "client-secret",
      "secret": "dev-secret",
      "attributes": {
        "access.token.lifespan": "6000"
      },
      "protocolMappers": [
        {
          "name": "user-scope",
          "protocol": "openid-connect",
          "protocolMapper": "oidc-usermodel-client-role-mapper",
          "consentRequired": false,
          "config": {
            "claim.name": "scope",
            "jsonType.label": "String",
            "multivalued": "true",
            "userinfo.token.claim": "true",
            "id.token.claim": "true",
            "access.token.claim": "true",
            "client.id": "notification-service"
          }
        }
      ]
    }
  ],
  "users": [
    {
      "username": "admin",
      "enabled": true,
      "email": "admin@example.com",
      "emailVerified": true,
      "requiredActions": [],
      "credentials": [
        {
          "type": "password",
          "value": "admin",
          "temporary": false
        }
      ],
      "clientRoles": {
        "notification-service": ["notifications:send"],
        "realm-management": [
          "manage-users",
          "view-users",
          "manage-realm",
          "manage-clients"
        ]
      }
    },
    {
      "username": "user1",
      "enabled": true,
      "email": "user1@example.com",
      "emailVerified": true,
      "credentials": [
        {
          "type": "user1",
          "value": "user1",
          "temporary": false
        }
      ],
      "attributes": {
        "sms": "+000000000001",
        "push": "392302",
        "preferred_notification_channel": "push"
      },
      "clientRoles": {
        "notification-service": []
      }
    },
    {
      "username": "user2",
      "enabled": true,
      "email": "user2@example.com",
      "emailVerified": true,
      "credentials": [
        {
          "type": "password",
          "value": "user2",
          "temporary": false
        }
      ],
      "attributes": {
        "telegram": "8123728",
        "push": "392303",
        "preferred_notification_channel": "email"
      },
      "clientRoles": {
        "notification-service": []
      }
    }
  ],
  "components": {
    "org.keycloak.userprofile.UserProfileProvider": [
      {
        "providerId": "declarative-user-profile",
        "subComponents": {},
        "config": {
          "kc.user.profile.config": [
            "{\"attributes\":[{\"name\":\"username\",\"displayName\":\"${username}\",\"validations\":{\"length\":{\"min\":3,\"max\":255},\"username-prohibited-characters\":{},\"up-username-not-idn-homograph\":{}},\"annotations\":{},\"permissions\":{\"view\":[\"admin\",\"user\"],\"edit\":[\"admin\",\"user\"]},\"multivalued\":false},{\"name\":\"email\",\"displayName\":\"${email}\",\"validations\":{\"email\":{},\"length\":{\"max\":255}},\"annotations\":{},\"required\":{\"roles\":[\"user\"]},\"permissions\":{\"view\":[\"admin\",\"user\"],\"edit\":[\"admin\",\"user\"]},\"group\":\"notification-channels\",\"multivalued\":false},{\"name\":\"firstName\",\"displayName\":\"${firstName}\",\"validations\":{\"length\":{\"max\":255},\"person-name-prohibited-characters\":{}},\"required\":{\"roles\":[\"user\"]},\"permissions\":{\"view\":[\"admin\",\"user\"],\"edit\":[\"admin\",\"user\"]},\"multivalued\":false},{\"name\":\"lastName\",\"displayName\":\"${lastName}\",\"validations\":{\"length\":{\"max\":255},\"person-name-prohibited-characters\":{}},\"required\":{\"roles\":[\"user\"]},\"permissions\":{\"view\":[\"admin\",\"user\"],\"edit\":[\"admin\",\"user\"]},\"multivalued\":false},{\"name\":\"sms\",\"displayName\":\"\",\"validations\":{},\"annotations\":{},\"permissions\":{\"view\":[],\"edit\":[\"admin\"]},\"group\":\"notification-channels\",\"multivalued\":false},{\"name\":\"push\",\"displayName\":\"\",\"validations\":{},\"annotations\":{},\"permissions\":{\"view\":[],\"edit\":[\"admin\"]},\"group\":\"notification-channels\",\"multivalued\":false},{\"name\":\"telegram\",\"displayName\":\"\",\"validations\":{},\"annotations\":{},\"permissions\":{\"view\":[],\"edit\":[\"admin\"]},\"group\":\"notification-channels\",\"multivalued\":false}],\"groups\":[{\"name\":\"user-metadata\",\"displayHeader\":\"User metadata\",\"displayDescription\":\"Attributes, which refer to user metadata\"},{\"name\":\"notification-channels\",\"displayHeader\":\"\",\"displayDescription\":\"\",\"annotations\":{}}]}"
          ]
        }
      }
    ]
  }
}
